[
    {
        "id": "board-22",
        "year": "2022-2023",
        "members": [
            {
                "id": "Executives-22",
                "people": [
                    {
                        "id": 1,
                        "position": "President",
                        "name": "Jamie Rice"
                    },
                    {
                        "id": 2,
                        "position": "VP Operations",
                        "name": "VACANT"
                    },
                    {
                        "id": 3,
                        "position": "VP Finance",
                        "name": "Redge Wang"
                    },
                    {
                        "id": 4,
                        "position": "VP Communications",
                        "name": "Tiam Vanaki"
                    },
                    {
                        "id": 5,
                        "position": "VP Student Life",
                        "name": "Anita Lesan"
                    },
                    {
                        "id": 6,
                        "position": "VP Academics",
                        "name": "Ramisa Razi"
                    },
                    {
                        "id": 7,
                        "position": "VP Externals",
                        "name": "VACANT"
                    },
                    {
                        "id": 8,
                        "position": "VP Equity",
                        "name": "Jafarul Hoque"
                    }
                ]
            },
            {
                "id": "Program Directors-22",
                "people": [
                    {
                        "id": 1,
                        "position": "Biomedical Science Directors",
                        "name": [
                            "Frank Garfalo",
                            "Golsa Malak",
                            "Urwa Najeeb"
                        ]
                    },
                    {
                        "id": 2,
                        "position": "Biology Director",
                        "name": [
                            "VACANT"
                        ]
                    },
                    {
                        "id": 3,
                        "position": "Chemistry Director",
                        "name": [
                            "Stephanie Tboas"
                        ]
                    },
                    {
                        "id": 4,
                        "position": "Computer Science Directors",
                        "name": [
                            "Mathushan Sivakumaran",
                            "VACANT",
                            "VACANT"
                        ]
                    },
                    {
                        "id": 5,
                        "position": "Mathematics and Its Applications Director",
                        "name": [
                            "Aisha Yusuf"
                        ]
                    },
                    {
                        "id": 6,
                        "position": "Financial Mathematics Director",
                        "name": [
                            "VACANT"
                        ]
                    },
                    {
                        "id": 7,
                        "position": "Medical Physics Director",
                        "name": [
                            "Alejandro Coba Cabrera"
                        ]
                    }
                ]
            },
            {
                "id": "First Year Directors-22",
                "people": [
                    {
                        "id": 1,
                        "position": "First-Year Director",
                        "name": "Louise Malabanan"
                    },
                    {
                        "id": 2,
                        "position": "First-Year Director",
                        "name": "Jack Shen"
                    },
                    {
                        "id": 3,
                        "position": "First-Year Director",
                        "name": "Benson Zhang"
                    }
                ]
            },
            {
                "id": "Non-Voting Members-22",
                "people": [
                    {
                        "id": 1,
                        "position": "Chairperson",
                        "name": "Alessandro Cunsolo"
                    },
                    {
                        "id": 2,
                        "position": "Manager, Student Relations and Development",
                        "name": "Pamela Wettlaufer"
                    },
                    {
                        "id": 3,
                        "position": "Secretary",
                        "name": "Nzonzila Mundele"
                    }
                ]
            }
        ]
    }
]